aPowerConverter/__init__.py
aPowerConverter/converter.py
apowerconverter-1.2.0.dist-info/licenses/LICENSE
apowerconverter-1.2.0.dist-info/METADATA
apowerconverter-1.2.0.dist-info/WHEEL
apowerconverter-1.2.0.dist-info/entry_points.txt
apowerconverter-1.2.0.dist-info/top_level.txt
apowerconverter-1.2.0.dist-info/RECORD
