Metadata-Version: 2.4
Name: aPowerConverter
Version: 1.2.0
Summary: A tool to convert DOCX files to AsciiDoc format with special table handling
Home-page: https://github.com/attoz/aPowerConverter
Author: attoz
Classifier: Programming Language :: Python :: 3
Classifier: License :: OSI Approved :: MIT License
Classifier: Operating System :: OS Independent
Requires-Python: >=3.6
License-File: LICENSE
Requires-Dist: pandoc
Dynamic: author
Dynamic: classifier
Dynamic: description
Dynamic: description-content-type
Dynamic: home-page
Dynamic: license-file
Dynamic: requires-dist
Dynamic: requires-python
Dynamic: summary
